pyfoal/__init__.py
pyfoal/__main__.py
pyfoal/checkpoint.py
pyfoal/convert.py
pyfoal/core.py
pyfoal/interpolate.py
pyfoal/load.py
pyfoal/loudness.py
pyfoal/model.py
pyfoal/time.py
pyfoal/viterbi.py
pyfoal/write.py
pyfoal/assets/g2p/phonemes.csv
pyfoal/assets/p2fa/config
pyfoal/assets/p2fa/hmmdefs
pyfoal/assets/p2fa/macros
pyfoal/assets/p2fa/monophones
pyfoal/assets/partitions/arctic.json
pyfoal/assets/partitions/libritts.json
pyfoal/baselines/__init__.py
pyfoal/baselines/mfa.py
pyfoal/baselines/p2fa.py
pyfoal/config/__init__.py
pyfoal/config/defaults.py
pyfoal/config/static.py
pyfoal/data/__init__.py
pyfoal/data/collate.py
pyfoal/data/dataset.py
pyfoal/data/loader.py
pyfoal/data/sampler.py
pyfoal/data/download/__init__.py
pyfoal/data/download/__main__.py
pyfoal/data/download/core.py
pyfoal/data/preprocess/__init__.py
pyfoal/data/preprocess/__main__.py
pyfoal/data/preprocess/core.py
pyfoal/data/preprocess/mels.py
pyfoal/data/preprocess/prior.py
pyfoal/evaluate/__init__.py
pyfoal/evaluate/__main__.py
pyfoal/evaluate/core.py
pyfoal/evaluate/metrics.py
pyfoal/g2p/__init__.py
pyfoal/g2p/core.py
pyfoal/partition/__init__.py
pyfoal/partition/__main__.py
pyfoal/partition/core.py
pyfoal/plot/__init__.py
pyfoal/plot/__main__.py
pyfoal/plot/core.py
pyfoal/train/__init__.py
pyfoal/train/__main__.py
pyfoal/train/core.py
pyfoal-1.0.1.dist-info/LICENSE
pyfoal-1.0.1.dist-info/METADATA
pyfoal-1.0.1.dist-info/WHEEL
pyfoal-1.0.1.dist-info/top_level.txt
pyfoal-1.0.1.dist-info/RECORD
