Metadata-Version: 2.1
Name: pyfoal
Version: 1.0.1
Summary: Python forced aligner
Home-page: https://github.com/maxrmorrison/pyfoal
Author: Max Morrison
Author-email: maxrmorrison@gmail.com
License: MIT
Keywords: align,alignment,attention,duration,phoneme,speech,word
Classifier: License :: OSI Approved :: MIT License
License-File: LICENSE
Requires-Dist: g2p-en
Requires-Dist: librosa
Requires-Dist: matplotlib
Requires-Dist: numpy
Requires-Dist: phonemizer
Requires-Dist: pypar
Requires-Dist: requests
Requires-Dist: scikit-learn
Requires-Dist: scipy
Requires-Dist: soundfile
Requires-Dist: tensorboard
Requires-Dist: torch
Requires-Dist: torchaudio
Requires-Dist: tqdm
Requires-Dist: yapecs
